templaterepo/__init__.py
templaterepo/_utils/__init__.py
templaterepo-0.1.3.dist-info/LICENSE.txt
templaterepo-0.1.3.dist-info/METADATA
templaterepo-0.1.3.dist-info/WHEEL
templaterepo-0.1.3.dist-info/top_level.txt
templaterepo-0.1.3.dist-info/RECORD
