Metadata-Version: 2.1
Name: templaterepo
Version: 0.1.3
License-File: LICENSE.txt
Requires-Dist: numpy
